bhashini_sdk/__init__.py
bhashini_sdk-0.0.1.dist-info/METADATA
bhashini_sdk-0.0.1.dist-info/WHEEL
bhashini_sdk-0.0.1.dist-info/RECORD
