Metadata-Version: 2.1
Name: bhashini-sdk
Version: 0.0.1
Summary: Bhashini SDK for Translation
Author: 'Abhinav Robinson'
Author-email: 'abhinavrobinson@gmail.com'
Requires-Python: >=3.9,<4.0
Classifier: Programming Language :: Python :: 3
Classifier: Programming Language :: Python :: 3.9
Classifier: Programming Language :: Python :: 3.10
Classifier: Programming Language :: Python :: 3.11
Classifier: Programming Language :: Python :: 3.12
